{"columns":[{"code":"KOHEZIJSKA IN STATISTIČNA REGIJA","text":"KOHEZIJSKA IN STATISTIČNA REGIJA","comment":"Podatki so teritorialno razvrščeni po Klasifikaciji statističnih teritorialnih enot v Evropski uniji (The Classification  of Territorial Units for Statistics) – NUTS (<A class='seznam' HREF=https://www.stat.si/StatWeb/sl/Methods/Classifications TARGET=_blank>opis in pojasnila</A>), raven NUTS 2 in raven NUTS 3. Opombe o spremembah posameznih regij so zapisane k vsaki spremenjeni regiji in so ob izpisu tabele na zaslon dostopne s klikom na ikono za opombe (zvezdica). V opombah je na začetku naveden datum, s katerim je opisana teritorialna sprememba upoštevana pri teritorialnem razvrščanju enot za statistične namene.\r\n","type":"d"},{"code":"LETO","text":"LETO","type":"t"},{"code":"MERITVE","text":"MERITVE","type":"d"},{"code":"Podjetja","text":"Podjetja","type":"c"}],"comments":[{"variable":"KOHEZIJSKA IN STATISTIČNA REGIJA","value":"06","comment":"Na podlagi spremembe Uredbe NUTS se je Spodnjeposavska NUTS 3 regija (statistična regija) preimenovala v Posavsko NUTS 3 regijo (statistično regijo) v 2015.\r\n"},{"variable":"KOHEZIJSKA IN STATISTIČNA REGIJA","value":"07","comment":"30. 3. 2000 je bil po Uredbi o SKTE iz dotedanje osrednjeslovenske statistične regije izločen njen južni del (občine Kočevje, Kostel, Loški Potok, Osilnica, Ribnica, Sodražica) in pripojen k dotedanji dolenjski statistični regiji; ta se je zato povečala (za  985 km2 ) in je dobila novo ime – Jugovzhodna Slovenija Uradni list št. 28/00.\r\n"},{"variable":"KOHEZIJSKA IN STATISTIČNA REGIJA","value":"10","comment":"Na podlagi spremembe Uredbe NUTS se je Notranjsko-kraška NUTS 3 regija (statistična regija) preimenovala v Primorsko-notranjsko NUTS 3 regijo (statistično regijo) v 2015.\r\n"},{"variable":"KOHEZIJSKA IN STATISTIČNA REGIJA","value":"08","comment":"30. 3. 2000 je bil po Uredbi o SKTE iz dotedanje osrednjeslovenske statistične regije izločen njen južni del (občine Kočevje, Kostel, Loški Potok, Osilnica, Ribnica, Sodražica) in pripojen k dotedanji dolenjski statistični regiji; ta se je zato povečala (za  985 km2 ) in je dobila novo ime – Jugovzhodna Slovenija Uradni list št. 28/00.\r\n"},{"variable":"MERITVE","value":"3","comment":"Je prodajna vrednost kupcem zaračunanih prodanih proizvodov ali trgovskega\r\nblaga in materiala ter opravljenih storitev. Meri se na podlagi prodajnih\r\ncen, navedenih v računih in drugih listinah, zmanjšanih za vse popuste, ki\r\nso bili dani ob prodaji ali pozneje, pa tudi za vrednosti vrnjenih\r\nkoličin. Prihodek zajema tudi vse stroške in obremenitve, vezane na kupca,\r\nne zajema pa davkov in carinskih dajatev na blago ali storitve, ki jih\r\nenota fakturira, in davka na dodano vrednost (DDV), morebitne prodaje\r\nosnovnih sredstev, prihodek od financiranja in drugih izrednih prihodkov.\r\nV podatku o prihodku podjetij je od 2013 tudi zajet prihodek bank in\r\nhranilnic.\r\nVsote se zaradi zaokroževanja včasih ne ujemajo.\r\n"}],"data":[{"key":["0","2008","3"],"values":["95786283"]},{"key":["0","2009","3"],"values":["83060213"]},{"key":["0","2010","3"],"values":["86705208"]},{"key":["0","2011","3"],"values":["90789676"]},{"key":["0","2012","3"],"values":["90754575"]},{"key":["0","2013","3"],"values":["90625516"]},{"key":["0","2014","3"],"values":["93571789"]},{"key":["0","2015","3"],"values":["95298760"]},{"key":["0","2016","3"],"values":["98573630"]},{"key":["0","2017","3"],"values":["108840205"]},{"key":["0","2018","3"],"values":["117040613"]},{"key":["0","2019","3"],"values":["121356615"]},{"key":["01","2008","3"],"values":["2680296"]},{"key":["01","2009","3"],"values":["2300870"]},{"key":["01","2010","3"],"values":["2305183"]},{"key":["01","2011","3"],"values":["2465323"]},{"key":["01","2012","3"],"values":["2615038"]},{"key":["01","2013","3"],"values":["2586958"]},{"key":["01","2014","3"],"values":["2859624"]},{"key":["01","2015","3"],"values":["2664445"]},{"key":["01","2016","3"],"values":["2836447"]},{"key":["01","2017","3"],"values":["3085418"]},{"key":["01","2018","3"],"values":["3293241"]},{"key":["01","2019","3"],"values":["3457867"]},{"key":["02","2008","3"],"values":["10955343"]},{"key":["02","2009","3"],"values":["9192508"]},{"key":["02","2010","3"],"values":["9632119"]},{"key":["02","2011","3"],"values":["10092169"]},{"key":["02","2012","3"],"values":["9865530"]},{"key":["02","2013","3"],"values":["9921339"]},{"key":["02","2014","3"],"values":["10293276"]},{"key":["02","2015","3"],"values":["10345996"]},{"key":["02","2016","3"],"values":["10451382"]},{"key":["02","2017","3"],"values":["11338221"]},{"key":["02","2018","3"],"values":["12171082"]},{"key":["02","2019","3"],"values":["12563498"]},{"key":["03","2008","3"],"values":["2283659"]},{"key":["03","2009","3"],"values":["1752657"]},{"key":["03","2010","3"],"values":["1840289"]},{"key":["03","2011","3"],"values":["2058028"]},{"key":["03","2012","3"],"values":["2020408"]},{"key":["03","2013","3"],"values":["1955143"]},{"key":["03","2014","3"],"values":["2021142"]},{"key":["03","2015","3"],"values":["2074703"]},{"key":["03","2016","3"],"values":["2140636"]},{"key":["03","2017","3"],"values":["2371561"]},{"key":["03","2018","3"],"values":["2506426"]},{"key":["03","2019","3"],"values":["2541586"]},{"key":["04","2008","3"],"values":["10013476"]},{"key":["04","2009","3"],"values":["8684503"]},{"key":["04","2010","3"],"values":["8973185"]},{"key":["04","2011","3"],"values":["9552070"]},{"key":["04","2012","3"],"values":["9211070"]},{"key":["04","2013","3"],"values":["9231084"]},{"key":["04","2014","3"],"values":["9376784"]},{"key":["04","2015","3"],"values":["9262353"]},{"key":["04","2016","3"],"values":["9600906"]},{"key":["04","2017","3"],"values":["10569994"]},{"key":["04","2018","3"],"values":["11176914"]},{"key":["04","2019","3"],"values":["11713716"]},{"key":["05","2008","3"],"values":["926541"]},{"key":["05","2009","3"],"values":["805109"]},{"key":["05","2010","3"],"values":["819967"]},{"key":["05","2011","3"],"values":["853627"]},{"key":["05","2012","3"],"values":["810821"]},{"key":["05","2013","3"],"values":["768467"]},{"key":["05","2014","3"],"values":["744714"]},{"key":["05","2015","3"],"values":["948515"]},{"key":["05","2016","3"],"values":["1007416"]},{"key":["05","2017","3"],"values":["1070188"]},{"key":["05","2018","3"],"values":["1172746"]},{"key":["05","2019","3"],"values":["1240596"]},{"key":["06","2008","3"],"values":["2049176"]},{"key":["06","2009","3"],"values":["2000585"]},{"key":["06","2010","3"],"values":["2155739"]},{"key":["06","2011","3"],"values":["2689568"]},{"key":["06","2012","3"],"values":["3172289"]},{"key":["06","2013","3"],"values":["2934390"]},{"key":["06","2014","3"],"values":["3031201"]},{"key":["06","2015","3"],"values":["3620580"]},{"key":["06","2016","3"],"values":["3587313"]},{"key":["06","2017","3"],"values":["4518845"]},{"key":["06","2018","3"],"values":["4678364"]},{"key":["06","2019","3"],"values":["4565657"]},{"key":["07","2008","3"],"values":["5961848"]},{"key":["07","2009","3"],"values":["5422208"]},{"key":["07","2010","3"],"values":["5728914"]},{"key":["07","2011","3"],"values":["5685052"]},{"key":["07","2012","3"],"values":["5445191"]},{"key":["07","2013","3"],"values":["5153151"]},{"key":["07","2014","3"],"values":["5452398"]},{"key":["07","2015","3"],"values":["5692304"]},{"key":["07","2016","3"],"values":["5980393"]},{"key":["07","2017","3"],"values":["7049338"]},{"key":["07","2018","3"],"values":["7740497"]},{"key":["07","2019","3"],"values":["8066922"]},{"key":["10","2008","3"],"values":["1303637"]},{"key":["10","2009","3"],"values":["1120466"]},{"key":["10","2010","3"],"values":["1209092"]},{"key":["10","2011","3"],"values":["1278751"]},{"key":["10","2012","3"],"values":["1255416"]},{"key":["10","2013","3"],"values":["1299627"]},{"key":["10","2014","3"],"values":["1431246"]},{"key":["10","2015","3"],"values":["1469335"]},{"key":["10","2016","3"],"values":["1467986"]},{"key":["10","2017","3"],"values":["1526911"]},{"key":["10","2018","3"],"values":["1654815"]},{"key":["10","2019","3"],"values":["1628734"]},{"key":["08","2008","3"],"values":["42402572"]},{"key":["08","2009","3"],"values":["37744272"]},{"key":["08","2010","3"],"values":["39188143"]},{"key":["08","2011","3"],"values":["40716581"]},{"key":["08","2012","3"],"values":["41309817"]},{"key":["08","2013","3"],"values":["41831525"]},{"key":["08","2014","3"],"values":["42837607"]},{"key":["08","2015","3"],"values":["43414618"]},{"key":["08","2016","3"],"values":["45134702"]},{"key":["08","2017","3"],"values":["49305366"]},{"key":["08","2018","3"],"values":["53286031"]},{"key":["08","2019","3"],"values":["55552497"]},{"key":["09","2008","3"],"values":["7185299"]},{"key":["09","2009","3"],"values":["5822294"]},{"key":["09","2010","3"],"values":["6213259"]},{"key":["09","2011","3"],"values":["6437933"]},{"key":["09","2012","3"],"values":["6457668"]},{"key":["09","2013","3"],"values":["6340948"]},{"key":["09","2014","3"],"values":["6700736"]},{"key":["09","2015","3"],"values":["6822608"]},{"key":["09","2016","3"],"values":["7074340"]},{"key":["09","2017","3"],"values":["7755200"]},{"key":["09","2018","3"],"values":["8405345"]},{"key":["09","2019","3"],"values":["8771500"]},{"key":["11","2008","3"],"values":["4448113"]},{"key":["11","2009","3"],"values":["3670648"]},{"key":["11","2010","3"],"values":["3885528"]},{"key":["11","2011","3"],"values":["4028942"]},{"key":["11","2012","3"],"values":["3838306"]},{"key":["11","2013","3"],"values":["3709793"]},{"key":["11","2014","3"],"values":["3852122"]},{"key":["11","2015","3"],"values":["3963455"]},{"key":["11","2016","3"],"values":["4122753"]},{"key":["11","2017","3"],"values":["4628201"]},{"key":["11","2018","3"],"values":["4725204"]},{"key":["11","2019","3"],"values":["4954688"]},{"key":["12","2008","3"],"values":["5576322"]},{"key":["12","2009","3"],"values":["4544093"]},{"key":["12","2010","3"],"values":["4753789"]},{"key":["12","2011","3"],"values":["4931630"]},{"key":["12","2012","3"],"values":["4753021"]},{"key":["12","2013","3"],"values":["4893091"]},{"key":["12","2014","3"],"values":["4970941"]},{"key":["12","2015","3"],"values":["5019848"]},{"key":["12","2016","3"],"values":["5169354"]},{"key":["12","2017","3"],"values":["5620960"]},{"key":["12","2018","3"],"values":["6229948"]},{"key":["12","2019","3"],"values":["6299354"]}],"metadata":[{"updated":"2008-11-05T09:30:00Z","label":"Podjetja po: KOHEZIJSKA IN STATISTIČNA REGIJA, LETO ,  MERITVE","source":"Statistični urad Republike Slovenije"}]}